alibabacloud_agentidentitydata20251127/__init__.py
alibabacloud_agentidentitydata20251127/client.py
alibabacloud_agentidentitydata20251127/models/__init__.py
alibabacloud_agentidentitydata20251127/models/_assume_role_for_workload_identity_request.py
alibabacloud_agentidentitydata20251127/models/_assume_role_for_workload_identity_response.py
alibabacloud_agentidentitydata20251127/models/_assume_role_for_workload_identity_response_body.py
alibabacloud_agentidentitydata20251127/models/_complete_resource_token_auth_request.py
alibabacloud_agentidentitydata20251127/models/_complete_resource_token_auth_response.py
alibabacloud_agentidentitydata20251127/models/_complete_resource_token_auth_response_body.py
alibabacloud_agentidentitydata20251127/models/_complete_resource_token_auth_shrink_request.py
alibabacloud_agentidentitydata20251127/models/_get_resource_apikey_request.py
alibabacloud_agentidentitydata20251127/models/_get_resource_apikey_response.py
alibabacloud_agentidentitydata20251127/models/_get_resource_apikey_response_body.py
alibabacloud_agentidentitydata20251127/models/_get_resource_oauth2_token_request.py
alibabacloud_agentidentitydata20251127/models/_get_resource_oauth2_token_response.py
alibabacloud_agentidentitydata20251127/models/_get_resource_oauth2_token_response_body.py
alibabacloud_agentidentitydata20251127/models/_get_resource_oauth2_token_shrink_request.py
alibabacloud_agentidentitydata20251127/models/_get_workload_access_token_for_jwt_request.py
alibabacloud_agentidentitydata20251127/models/_get_workload_access_token_for_jwt_response.py
alibabacloud_agentidentitydata20251127/models/_get_workload_access_token_for_jwt_response_body.py
alibabacloud_agentidentitydata20251127/models/_get_workload_access_token_for_user_id_request.py
alibabacloud_agentidentitydata20251127/models/_get_workload_access_token_for_user_id_response.py
alibabacloud_agentidentitydata20251127/models/_get_workload_access_token_for_user_id_response_body.py
alibabacloud_agentidentitydata20251127-2.0.0.dist-info/LICENSE
alibabacloud_agentidentitydata20251127-2.0.0.dist-info/METADATA
alibabacloud_agentidentitydata20251127-2.0.0.dist-info/WHEEL
alibabacloud_agentidentitydata20251127-2.0.0.dist-info/top_level.txt
alibabacloud_agentidentitydata20251127-2.0.0.dist-info/RECORD
